nitrix/__init__.py
nitrix/docutil.py
nitrix/resid.py
nitrix/util.py
nitrix-0.0.0.dev0.dist-info/LICENSE
nitrix-0.0.0.dev0.dist-info/METADATA
nitrix-0.0.0.dev0.dist-info/WHEEL
nitrix-0.0.0.dev0.dist-info/top_level.txt
nitrix-0.0.0.dev0.dist-info/RECORD
