Metadata-Version: 2.1
Name: nitrix
Version: 0.0.0.dev0
Summary: Neuroimaging transformations in XLA
Author-email: Rastko Ciric <rastko@stanford.edu>
Maintainer-email: Rastko Ciric <rastko@stanford.edu>
License: Apache License
Project-URL: Homepage, https://github.com/hypercoil/nitrix
Classifier: Programming Language :: Python :: 3
Classifier: License :: OSI Approved :: Apache Software License
Classifier: Operating System :: POSIX :: Linux
Classifier: Operating System :: MacOS :: MacOS X
Requires-Python: >=3.10
License-File: LICENSE
Requires-Dist: jax >=0.3.16
Requires-Dist: numpy >=1.22.4
Provides-Extra: dev
Requires-Dist: pytest ; extra == 'dev'
Requires-Dist: pytest-cov ; extra == 'dev'
Requires-Dist: coverage[toml] ; extra == 'dev'
Requires-Dist: ruff ; extra == 'dev'
